LICENSE
README.md
setup.py
smarterjson/__init__.py
smarterjson/view.py
smarterjson.egg-info/PKG-INFO
smarterjson.egg-info/SOURCES.txt
smarterjson.egg-info/dependency_links.txt
smarterjson.egg-info/top_level.txt