Metadata-Version: 2.1
Name: smarterjson
Version: 1.3.5
Summary: A smarter than python json
Home-page: https://github.com/0x22f1a6543a0/smarterjsons
Author: Zhang Jiaqi
Author-email: 2953911716@qq.com
License: MIT
Classifier: Topic :: Software Development :: Build Tools
Classifier: License :: OSI Approved :: MIT License
Classifier: Programming Language :: Python :: 3
License-File: LICENSE
